odoo/addons/dms_attachment_link/README.rst
odoo/addons/dms_attachment_link/__init__.py
odoo/addons/dms_attachment_link/__manifest__.py
odoo/addons/dms_attachment_link/i18n/dms_attachment_link.pot
odoo/addons/dms_attachment_link/i18n/es.po
odoo/addons/dms_attachment_link/i18n/it.po
odoo/addons/dms_attachment_link/models/__init__.py
odoo/addons/dms_attachment_link/models/dms_file.py
odoo/addons/dms_attachment_link/models/ir_attachment.py
odoo/addons/dms_attachment_link/models/ir_binary.py
odoo/addons/dms_attachment_link/readme/CONTRIBUTORS.md
odoo/addons/dms_attachment_link/readme/DESCRIPTION.md
odoo/addons/dms_attachment_link/readme/USAGE.md
odoo/addons/dms_attachment_link/static/description/icon.png
odoo/addons/dms_attachment_link/static/description/icon.svg
odoo/addons/dms_attachment_link/static/description/index.html
odoo/addons/dms_attachment_link/static/src/js/dms_attachment_link.esm.js
odoo/addons/dms_attachment_link/static/src/xml/chatter.xml
odoo/addons/dms_attachment_link/tests/__init__.py
odoo/addons/dms_attachment_link/tests/test_dms_attachment_link.py
odoo/addons/dms_attachment_link/views/dms_file_views.xml
odoo_addon_dms_attachment_link-17.0.1.0.1.2.dist-info/METADATA
odoo_addon_dms_attachment_link-17.0.1.0.1.2.dist-info/WHEEL
odoo_addon_dms_attachment_link-17.0.1.0.1.2.dist-info/top_level.txt
odoo_addon_dms_attachment_link-17.0.1.0.1.2.dist-info/RECORD
